tk_base_utils/__init__.py
tk_base_utils/date.py
tk_base_utils/file.py
tk_base_utils/list.py
tk_base_utils/toml.py
tk_base_utils/path_module/__init__.py
tk_base_utils/path_module/get_path_dir.py
tk_base_utils/tk_http/__init__.py
tk_base_utils/tk_http/client.py
tk_base_utils/tk_http/config.py
tk_base_utils/tk_http/exceptions.py
tk_base_utils/tk_http/logger.py
tk_base_utils/tk_http/models.py
tk_base_utils/tk_http/retry.py
tk_base_utils/tk_logger/__init__.py
tk_base_utils/tk_logger/config.py
tk_base_utils/tk_logger/decorators.py
tk_base_utils/tk_logger/levels.py
tk_base_utils/tk_logger/logger.py
tk_base_utils-0.3.5.dist-info/licenses/LICENSE
tk_base_utils-0.3.5.dist-info/METADATA
tk_base_utils-0.3.5.dist-info/WHEEL
tk_base_utils-0.3.5.dist-info/top_level.txt
tk_base_utils-0.3.5.dist-info/RECORD
