Metadata-Version: 2.4
Name: tk-base-utils
Version: 0.3.5
Summary: Add your description here
Requires-Python: >=3.11
License-File: LICENSE
Requires-Dist: httpx>=0.28.1
Requires-Dist: pydantic>=2.11.7
Dynamic: license-file
